Metadata-Version: 2.1
Name: cffi-glpk
Version: 0.5
Summary: CFFI bindings for GLPK
Home-page: https://github.com/cfblaeb/cffi_glpk
Author: laeb
Author-email: laeb@dtu.dk
License: UNKNOWN
Platform: UNKNOWN
